<?xml version='1.0' encoding='UTF-8'?>
<fingerprint>
  <timestamp>2017-10-31 14:30:23.593 UTC</timestamp>
  <original>
    <name>services/maven-counter/com.mkyong:CounterWebApp</name>
    <number>3</number>
  </original>
  <md5sum>3f132496dd71e4a656de87ddcdf48935</md5sum>
  <fileName>com.mkyong:CounterWebApp:pom.xml</fileName>
  <usages>
    <entry>
      <string>services/maven-counter/com.mkyong:CounterWebApp</string>
      <ranges>3-5</ranges>
    </entry>
    <entry>
      <string>services/maven-counter</string>
      <ranges>3-5</ranges>
    </entry>
  </usages>
  <facets/>
</fingerprint>